seeq/addons/azureml/__init__.py
seeq/addons/azureml/__main__.py
seeq/addons/azureml/_add_on_main.py
seeq/addons/azureml/_config.py
seeq/addons/azureml/_copy.py
seeq/addons/azureml/_version.py
seeq/addons/azureml/backend/__init__.py
seeq/addons/azureml/backend/_aml_online_endpoint_service.py
seeq/addons/azureml/backend/_aml_response_models.py
seeq/addons/azureml/backend/_run_investigation.py
seeq/addons/azureml/backend/_seeq_inputs_provider.py
seeq/addons/azureml/deployment_notebook/azureml_integration_deploy_model.ipynb
seeq/addons/azureml/deployment_notebook/azureml_integration_master.ipynb
seeq/addons/azureml/ui_components/__init__.py
seeq/addons/azureml/ui_components/_app_layout.py
seeq/addons/azureml/ui_components/_hamburger_menu.py
seeq/addons/azureml/ui_components/_investigate_range.py
seeq/addons/azureml/ui_components/_model_action.py
seeq/addons/azureml/ui_components/_model_inputs.py
seeq/addons/azureml/ui_components/_model_summary.py
seeq/addons/azureml/ui_components/_schedule_inputs.py
seeq/addons/azureml/ui_components/templates/_app_layout.vue
seeq/addons/azureml/ui_components/templates/_hamburger_menu.vue
seeq/addons/azureml/ui_components/templates/_investigate_range.vue
seeq/addons/azureml/ui_components/templates/_model_action.vue
seeq/addons/azureml/ui_components/templates/_model_inputs.vue
seeq/addons/azureml/ui_components/templates/_model_summary.vue
seeq/addons/azureml/ui_components/templates/_schedule_inputs.vue
seeq/addons/azureml/utils/__init__.py
seeq/addons/azureml/utils/_exceptions.py
seeq/addons/azureml/utils/_sdl.py
seeq_azureml-0.1.3.dist-info/LICENSE
seeq_azureml-0.1.3.dist-info/METADATA
seeq_azureml-0.1.3.dist-info/NOTICE
seeq_azureml-0.1.3.dist-info/WHEEL
seeq_azureml-0.1.3.dist-info/top_level.txt
seeq_azureml-0.1.3.dist-info/RECORD
