Metadata-Version: 2.1
Name: seeq-azureml
Version: 0.1.3
Summary: Seeq Add-on that integrates with Microsoft Azure Machine Learning (AML) models as a web service
Home-page: https://github.com/seeq12/seeq-azureml
Author: Seeq Corporation
Author-email: applied.research@seeq.com
License: Apache License 2.0
Platform: UNKNOWN
Classifier: Programming Language :: Python :: 3.7
Classifier: License :: OSI Approved :: Apache Software License
Classifier: Operating System :: OS Independent
Requires-Python: >=3.7
License-File: LICENSE
License-File: NOTICE
Requires-Dist: ipywidgets (>=7.6.3)
Requires-Dist: ipyvuetify (>=1.8.0)
Requires-Dist: numpy (>=1.19.5)
Requires-Dist: pandas (~=1.2.5)
Requires-Dist: requests (>=2.26.0)
Requires-Dist: traitlets (>=5.1.0)
Requires-Dist: ipydatetime (>=1.2.0)
